pygrnd/__init__.py
pygrnd/optimize/MonteCarloSolver.py
pygrnd/optimize/UCPquboFunctionLibrary.py
pygrnd/optimize/__init__.py
pygrnd/optimize/bruteforce.py
pygrnd/optimize/meritorder.py
pygrnd/optimize/qaoa.py
pygrnd/optimize/qmco.py
pygrnd/optimize/sat_ucp.py
pygrnd/qc/MaximumLikelihoodForQAEwoPE.py
pygrnd/qc/QAE.py
pygrnd/qc/__init__.py
pygrnd/qc/brm.py
pygrnd/qc/brm_oracle.py
pygrnd/qc/brm_test.py
pygrnd/qc/circuitConstructor.py
pygrnd/qc/circuitConstructor_test.py
pygrnd/qc/helper.py
pygrnd/qc/lowDepthQAEgradientDescent.py
pygrnd/qc/optimize.py
pygrnd/qc/parallelQAE.py
pygrnd/qc/patternGenerator.py
pygrnd/qc/patternReducer.py
pygrnd/qc/probabilisticNetworks.py
pygrnd/qc/qml.py
pygrnd-0.1.8.dist-info/LICENSE
pygrnd-0.1.8.dist-info/METADATA
pygrnd-0.1.8.dist-info/WHEEL
pygrnd-0.1.8.dist-info/top_level.txt
pygrnd-0.1.8.dist-info/RECORD
