Metadata-Version: 2.2
Name: pygrnd
Version: 0.1.8
Summary: A python library for quantum algorithms and software
Home-page: https://github.com/JoSQUANTUM/pygrnd
Author: JoS QUANTUM
Author-email: contact@jos-quantum.de
License: Apache 2.0
Classifier: Programming Language :: Python :: 3
Classifier: License :: OSI Approved :: Apache Software License
Classifier: Operating System :: OS Independent
License-File: LICENSE
Requires-Dist: qiskit
Requires-Dist: numpy
Requires-Dist: dimod
Requires-Dist: dwave-greedy
Requires-Dist: dwave-neal
Requires-Dist: pennylane
Requires-Dist: pandas
Requires-Dist: seaborn
Requires-Dist: tqdm
Requires-Dist: pylatexenc
Requires-Dist: scikit-learn
Requires-Dist: DateTime
Requires-Dist: shap
Requires-Dist: xgboost
Requires-Dist: holidays
Requires-Dist: imblearn
Dynamic: author
Dynamic: author-email
Dynamic: classifier
Dynamic: description
Dynamic: description-content-type
Dynamic: home-page
Dynamic: license
Dynamic: requires-dist
Dynamic: summary
